odoo/addons/mass_mailing_resend/README.rst
odoo/addons/mass_mailing_resend/__init__.py
odoo/addons/mass_mailing_resend/__manifest__.py
odoo/addons/mass_mailing_resend/i18n/ca.po
odoo/addons/mass_mailing_resend/i18n/de.po
odoo/addons/mass_mailing_resend/i18n/es.po
odoo/addons/mass_mailing_resend/i18n/fr.po
odoo/addons/mass_mailing_resend/i18n/it.po
odoo/addons/mass_mailing_resend/i18n/mass_mailing_resend.pot
odoo/addons/mass_mailing_resend/i18n/sl.po
odoo/addons/mass_mailing_resend/models/__init__.py
odoo/addons/mass_mailing_resend/models/mailing_mailing.py
odoo/addons/mass_mailing_resend/readme/CONTRIBUTORS.md
odoo/addons/mass_mailing_resend/readme/DESCRIPTION.md
odoo/addons/mass_mailing_resend/readme/ROADMAP.md
odoo/addons/mass_mailing_resend/readme/USAGE.md
odoo/addons/mass_mailing_resend/static/description/icon.png
odoo/addons/mass_mailing_resend/static/description/icon.svg
odoo/addons/mass_mailing_resend/static/description/index.html
odoo/addons/mass_mailing_resend/tests/__init__.py
odoo/addons/mass_mailing_resend/tests/test_mass_mailing_resend.py
odoo/addons/mass_mailing_resend/views/mailing_mailing_views.xml
odoo_addon_mass_mailing_resend-18.0.1.0.0.2.dist-info/METADATA
odoo_addon_mass_mailing_resend-18.0.1.0.0.2.dist-info/WHEEL
odoo_addon_mass_mailing_resend-18.0.1.0.0.2.dist-info/top_level.txt
odoo_addon_mass_mailing_resend-18.0.1.0.0.2.dist-info/RECORD
